flask_toolkits/__init__.py
flask_toolkits/dependencies.py
flask_toolkits/exceptions.py
flask_toolkits/fields.py
flask_toolkits/middleware.py
flask_toolkits/params.py
flask_toolkits/responses.py
flask_toolkits/routing.py
flask_toolkits/schemas.py
flask_toolkits/security.py
flask_toolkits/status.py
flask_toolkits/swagger/__init__.py
flask_toolkits/swagger/flask_swagger_ui.py
flask_toolkits/swagger/swagger.py
flask_toolkits/swagger/template.py
flask_toolkits/swagger/dist/favicon-16x16.png
flask_toolkits/swagger/dist/favicon-32x32.png
flask_toolkits/swagger/dist/index.css
flask_toolkits/swagger/dist/index.html
flask_toolkits/swagger/dist/oauth2-redirect.html
flask_toolkits/swagger/dist/swagger-initializer.js
flask_toolkits/swagger/dist/swagger-ui-bundle.js
flask_toolkits/swagger/dist/swagger-ui-es-bundle-core.js
flask_toolkits/swagger/dist/swagger-ui-es-bundle.js
flask_toolkits/swagger/dist/swagger-ui-standalone-preset.js
flask_toolkits/swagger/dist/swagger-ui.css
flask_toolkits/swagger/dist/swagger-ui.js
flask_toolkits/swagger/templates/index.template.html
flask_toolkits-0.7.10.dist-info/LICENSE
flask_toolkits-0.7.10.dist-info/METADATA
flask_toolkits-0.7.10.dist-info/WHEEL
flask_toolkits-0.7.10.dist-info/top_level.txt
flask_toolkits-0.7.10.dist-info/RECORD
