Metadata-Version: 2.1
Name: flask-toolkits
Version: 0.7.10
Summary: Flask toolkits to boost your development and simplify flask, its featured with AutoSwagger
Home-page: https://github.com/Danangjoyoo/flask-toolkits
Author: danangjoyoo (Agus Danangjoyo)
Author-email: <agus.danangjoyo.blog@gmail.com>
Keywords: flask,middleware,http,request,response,swagger,openapi,toolkit
Classifier: Development Status :: 4 - Beta
Classifier: Intended Audience :: Developers
Classifier: Programming Language :: Python :: 3 :: Only
Classifier: Programming Language :: Python :: 3.6
Classifier: Programming Language :: Python :: 3.7
Classifier: Programming Language :: Python :: 3.8
Classifier: Programming Language :: Python :: 3.9
Classifier: Programming Language :: Python :: 3.10
Classifier: Environment :: Web Environment
Classifier: Operating System :: OS Independent
Classifier: Typing :: Typed
License-File: LICENSE
Requires-Dist: flask (>=2.0.0)
Requires-Dist: werkzeug (>=2.0.0)
Requires-Dist: flask-http-middleware
Requires-Dist: pydantic
Requires-Dist: python-jose
